validation/__init__.py
validation/adval.py
adval-0.0.9.dist-info/LICENSE.txt
adval-0.0.9.dist-info/METADATA
adval-0.0.9.dist-info/WHEEL
adval-0.0.9.dist-info/top_level.txt
adval-0.0.9.dist-info/RECORD
